labnode_async/__init__.py
labnode_async/_version.py
labnode_async/connection.py
labnode_async/device_factory.py
labnode_async/devices.py
labnode_async/errors.py
labnode_async/ip_connection.py
labnode_async/labnode.py
labnode_async/pid_controller.py
labnode_async/serial_connection.py
labnode_async-0.16.4.dist-info/LICENSE
labnode_async-0.16.4.dist-info/METADATA
labnode_async-0.16.4.dist-info/WHEEL
labnode_async-0.16.4.dist-info/top_level.txt
labnode_async-0.16.4.dist-info/RECORD
