Metadata-Version: 2.1
Name: labnode-async
Version: 0.16.4
Summary: Python3 AsyncIO Labnode driver
Author-email: Patrick Baus <patrick.baus@physik.tu-darmstadt.de>
License: GNU General Public License v3 (GPLv3)
Project-URL: Homepage, https://github.com/PatrickBaus/labnode_async
Project-URL: Bug Tracker, https://github.com/PatrickBaus/labnode_async/issues
Project-URL: Download, https://github.com/PatrickBaus/labnode_async/releases
Project-URL: Documentation, https://patrickbaus.github.io/labnode_async/
Keywords: IoT,PID,PID controller,API
Classifier: Programming Language :: Python :: 3
Classifier: Programming Language :: Python :: 3.7
Classifier: Programming Language :: Python :: 3.8
Classifier: Programming Language :: Python :: 3.9
Classifier: Programming Language :: Python :: 3.10
Classifier: Programming Language :: Python :: 3.11
Classifier: Development Status :: 5 - Production/Stable
Classifier: License :: OSI Approved :: GNU General Public License v3 (GPLv3)
Classifier: Operating System :: OS Independent
Classifier: Intended Audience :: Developers
Classifier: Intended Audience :: Science/Research
Classifier: Natural Language :: English
Classifier: Topic :: Home Automation
Classifier: Topic :: Scientific/Engineering
Requires-Python: >=3.7
License-File: LICENSE
Requires-Dist: cbor2
Requires-Dist: cobs
Requires-Dist: pyserial-asyncio
Requires-Dist: typing-extensions ; python_version < "3.11"
Provides-Extra: dev
Requires-Dist: black ; extra == 'dev'
Requires-Dist: build ; extra == 'dev'
Requires-Dist: isort ; extra == 'dev'
Requires-Dist: mypy ; extra == 'dev'
Requires-Dist: pre-commit ; extra == 'dev'
Requires-Dist: pylint ; extra == 'dev'
Requires-Dist: pytest ; extra == 'dev'
Requires-Dist: twine ; extra == 'dev'
Provides-Extra: doc
Requires-Dist: myst-parser ; extra == 'doc'
Requires-Dist: sphinx ; extra == 'doc'
Provides-Extra: test
Requires-Dist: mypy ; extra == 'test'
Requires-Dist: pylint ; extra == 'test'
Requires-Dist: pytest ; extra == 'test'
